LICENSE
README.md
setup.py
rgl/__init__.py
rgl.egg-info/PKG-INFO
rgl.egg-info/SOURCES.txt
rgl.egg-info/dependency_links.txt
rgl.egg-info/requires.txt
rgl.egg-info/top_level.txt
rgl/data/__init__.py
rgl/data/dataset.py
rgl/datasets/__init__.py
rgl/datasets/citation_graph.py
rgl/datasets/citeseer.py
rgl/datasets/mm_graph.py
rgl/datasets/ogb.py
rgl/datasets/pubmed.py
rgl/graph_retrieval/__init__.py
rgl/graph_retrieval/libretrieval.cpython-310-x86_64-linux-gnu.so
rgl/graph_retrieval/libretrieval.cpython-311-x86_64-linux-gnu.so
rgl/graph_retrieval/libretrieval.cpython-312-x86_64-linux-gnu.so
rgl/graph_retrieval/libretrieval.cpython-313-x86_64-linux-gnu.so
rgl/graph_retrieval/libretrieval.cpython-37m-x86_64-linux-gnu.so
rgl/graph_retrieval/libretrieval.cpython-38-x86_64-linux-gnu.so
rgl/graph_retrieval/libretrieval.cpython-39-x86_64-linux-gnu.so
rgl/graph_retrieval/retrieve.py
rgl/node_retrieval/__init__.py
rgl/node_retrieval/vector_search.py
rgl/utils/__init__.py
rgl/utils/data_utils.py
rgl/utils/llm_utils.py
rgl/utils/utils.py