Metadata-Version: 2.2
Name: rgl
Version: 0.0.4
Summary: RGL - RAG-on-Graphs Library
Home-page: https://github.com/PyRGL/rgl
Author: anthonynus
Author-email: e0403849@u.nus.edu
License: GNU General Public License v3.0 (See LICENSE)
Requires-Python: >3.7.0
License-File: LICENSE
Requires-Dist: ogb
Requires-Dist: patool
Requires-Dist: faiss-cpu
Requires-Dist: rouge-score
Requires-Dist: gradio
Dynamic: author
Dynamic: author-email
Dynamic: description
Dynamic: description-content-type
Dynamic: home-page
Dynamic: license
Dynamic: requires-dist
Dynamic: requires-python
Dynamic: summary
